{"item-id":"2CCQFDVWPP3HV2WC7R2I2PWUZ2AWQUBM","facet":[{"@name":"time_fct","value":["time_61600","time_61605"]},{"@name":"place_fct_normdata","value":"http://d-nb.info/gnd/8214-4"},{"@name":"place_fct","value":"Göttingen"},{"@name":"affiliate_fct","value":["Geiler von Keiserberg, Johannes","Grieninger"]},{"@name":"affiliate_fct_role","value":["Geiler von Keiserberg, Johannes","Grieninger","Geiler von Keiserberg, Johannes_1_affiliate_fct_involved","Grieninger_1_affiliate_fct_involved"]},{"@name":"keywords_fct","value":["Monographie","Bucherhaltung","Varia"]},{"@name":"language_fct","value":"ger"},{"@name":"type_fct","value":"mediatype_003"},{"@name":"sector_fct","value":"sec_02"},{"@name":"provider_fct","value":["zvdd – Zentrales Verzeichnis Digitalisierter Drucke","Niedersächsische Staats- und Universitätsbibliothek Göttingen","Georg-August-Universität Göttingen"]},{"@name":"last_update","value":"14-03-06 18:57:01"}]}