{"item-id":"2ECULMXHZCWLABJNDO6QKDKHR57IQRT7","facet":[{"@name":"time_fct","value":["time_61947","time_61900"]},{"@name":"place_fct","value":["Île-de-France","Paris, Département","Paris","Frankreich"]},{"@name":"affiliate_fct","value":["Médiathèque de l'architecture et du patrimoine — Archives des Monuments historiques (Paris)","Leblan, Henri Eugène"]},{"@name":"keywords_fct","value":["Schnitt","Zeichenkunst?"]},{"@name":"type_fct","value":"mediatype_002"},{"@name":"sector_fct","value":"sec_04"},{"@name":"provider_fct","value":"Deutsches Dokumentationszentrum für Kunstgeschichte - Bildarchiv Foto Marburg"},{"@name":"category","value":"Kultur"},{"@name":"last_update","value":"12-12-17 23:14:31"}]}