{
    "time_fct_id": 9,
    "time_fct": "time_62120",
    "from_affiliate_facet_id": 70442,
    "from_affiliate_facet": "Boysen, Barbara",
    "occurrence": 18,
    "affiliates": [
        {
            "facet_id": 3100,
            "occurrence": 18,
            "value": "Universitätsbibliothek der Universität Stuttgart"
        },
        {
            "facet_id": 68799,
            "occurrence": 18,
            "value": "Voß, Alfred"
        },
        {
            "facet_id": 70442,
            "occurrence": 18,
            "value": "Boysen, Barbara"
        },
        {
            "facet_id": 133455,
            "occurrence": 18,
            "value": "Friedrich, Rainer"
        },
        {
            "facet_id": 133456,
            "occurrence": 9,
            "value": "Mattis, Marcus"
        },
        {
            "facet_id": 212678,
            "occurrence": 9,
            "value": "Müller, Thomas"
        },
        {
            "facet_id": 6021,
            "occurrence": 3,
            "value": "Fahl, Ulrich"
        },
        {
            "facet_id": 300131,
            "occurrence": 3,
            "value": "Obermeier, Andreas"
        },
        {
            "facet_id": 68798,
            "occurrence": 2,
            "value": "Kaltschmitt, Martin"
        },
        {
            "facet_id": 236846,
            "occurrence": 2,
            "value": "Kuntze, Richard"
        },
        {
            "facet_id": 236847,
            "occurrence": 2,
            "value": "Giesecke, Jürgen"
        },
        {
            "facet_id": 236848,
            "occurrence": 2,
            "value": "Jorde, Klaus"
        },
        {
            "facet_id": 236849,
            "occurrence": 2,
            "value": "Voigt, C."
        },
        {
            "facet_id": 236850,
            "occurrence": 2,
            "value": "Institut für Energiewirtschaft und Rationelle Energieanwendung <Stuttgart> / Abteilung Energiewirtschaft und Umwelt"
        },
        {
            "facet_id": 538643,
            "occurrence": 2,
            "value": "Scheirle, Nicolaus"
        },
        {
            "facet_id": 6023,
            "occurrence": 1,
            "value": "Liebscher, Peter"
        },
        {
            "facet_id": 853656,
            "occurrence": 1,
            "value": "Baessler, Rudolf"
        }
    ]
}