{
    "time_fct_id": 6,
    "time_fct": "time_62020",
    "affiliate_fct_id": 5055,
    "affiliate_fct": "Dix, Otto",
    "affiliate_fct_occurrence": 354,
    "affiliates": [
        {
            "affiliate_fct_id": 5055,
            "affiliate_fct": "Dix, Otto",
            "affiliate_fct_occurrence": 354
        },
        {
            "affiliate_fct_id": 13284,
            "affiliate_fct": "Otto Dix Stiftung (Vaduz)",
            "affiliate_fct_occurrence": 96
        },
        {
            "affiliate_fct_id": 2282,
            "affiliate_fct": "private Sammlung (München)",
            "affiliate_fct_occurrence": 34
        },
        {
            "affiliate_fct_id": 77761,
            "affiliate_fct": "Galerie Nierendorf (Berlin)",
            "affiliate_fct_occurrence": 16
        },
        {
            "affiliate_fct_id": 61,
            "affiliate_fct": "Richter, Regine (Fotograf)",
            "affiliate_fct_occurrence": 4
        },
        {
            "affiliate_fct_id": 15722,
            "affiliate_fct": "Kunstmuseum (Düsseldorf)",
            "affiliate_fct_occurrence": 4
        },
        {
            "affiliate_fct_id": 434043,
            "affiliate_fct": "Leopold-Hoesch-Museum (Düren)",
            "affiliate_fct_occurrence": 3
        },
        {
            "affiliate_fct_id": 2073,
            "affiliate_fct": "Staatliche Museen zu Berlin - Preußischer Kulturbesitz — Kupferstichkabinett - Sammlung der Zeichnungen und Druckgraphik (Berlin)",
            "affiliate_fct_occurrence": 2
        },
        {
            "affiliate_fct_id": 1756,
            "affiliate_fct": "Kunsthalle zu Kiel",
            "affiliate_fct_occurrence": 1
        },
        {
            "affiliate_fct_id": 2033,
            "affiliate_fct": "Von der Heydt-Museum (Wuppertal)",
            "affiliate_fct_occurrence": 1
        },
        {
            "affiliate_fct_id": 5155,
            "affiliate_fct": "private Sammlung (Berlin)",
            "affiliate_fct_occurrence": 1
        },
        {
            "affiliate_fct_id": 8440,
            "affiliate_fct": "Städtische Museen — Augustinermuseum (Freiburg im Breisgau)",
            "affiliate_fct_occurrence": 1
        },
        {
            "affiliate_fct_id": 34729,
            "affiliate_fct": "Staatsgalerie — Graphische Sammlung (Stuttgart)",
            "affiliate_fct_occurrence": 1
        },
        {
            "affiliate_fct_id": 37172,
            "affiliate_fct": "Museum der Stadt Ulm (Ulm)",
            "affiliate_fct_occurrence": 1
        },
        {
            "affiliate_fct_id": 61931,
            "affiliate_fct": "private Sammlung (Braunschweig)",
            "affiliate_fct_occurrence": 1
        },
        {
            "affiliate_fct_id": 63159,
            "affiliate_fct": "private Sammlung (Konstanz)",
            "affiliate_fct_occurrence": 1
        },
        {
            "affiliate_fct_id": 169178,
            "affiliate_fct": "Kunsthaus Lempertz (Köln)",
            "affiliate_fct_occurrence": 1
        },
        {
            "affiliate_fct_id": 775374,
            "affiliate_fct": "Hauswedell und Nolte (Hamburg)",
            "affiliate_fct_occurrence": 1
        },
        {
            "affiliate_fct_id": 885831,
            "affiliate_fct": "private Sammlung (Gera)",
            "affiliate_fct_occurrence": 1
        },
        {
            "affiliate_fct_id": 1034319,
            "affiliate_fct": "Karl und Faber (München)",
            "affiliate_fct_occurrence": 1
        }
    ]
}