{
    "time_fct_id": 10,
    "time_fct": "time_61925",
    "affiliate_facet_id": 1265,
    "affiliate_facet": "Zensurkommission",
    "occurrence": 1002,
    "affiliates": [
        {
            "facet_id": 1265,
            "occurrence": 1126,
            "value": "Reimer"
        },
        {
            "facet_id": 3917,
            "occurrence": 169,
            "value": "Paul, Jean (1763-1825)"
        },
        {
            "facet_id": 26217,
            "occurrence": 105,
            "value": "Tieck, Ludwig (1773-1853)"
        },
        {
            "facet_id": 16031,
            "occurrence": 49,
            "value": "Karsten, Carl J. B. (1782-1853)"
        },
        {
            "facet_id": 9705,
            "occurrence": 40,
            "value": "Schlegel, August Wilhelm von (1767-1845)"
        },
        {
            "facet_id": 5255,
            "occurrence": 38,
            "value": "Shakespeare, William (1564-1616)"
        },
        {
            "facet_id": 7835,
            "occurrence": 34,
            "value": "Schleiermacher, Friedrich (1768-1834)"
        },
        {
            "facet_id": 75887,
            "occurrence": 34,
            "value": "Ideler, Julius Ludwig (1809-1842)"
        },
        {
            "facet_id": 75886,
            "occurrence": 31,
            "value": "Ritter, Carl (1779-1859)"
        },
        {
            "facet_id": 75888,
            "occurrence": 30,
            "value": "Müller, Georg Friedrich Hermann"
        },
        {
            "facet_id": 28453,
            "occurrence": 25,
            "value": "Bekker, Immanuel (1785-1871)"
        },
        {
            "facet_id": 684,
            "occurrence": 23,
            "value": "Horn, Ernst (1774-1848)"
        },
        {
            "facet_id": 68392,
            "occurrence": 19,
            "value": "Hoffmann, E. T. A. (1776-1822)"
        },
        {
            "facet_id": 1097,
            "occurrence": 16,
            "value": "Aristoteles (v384-v322)"
        },
        {
            "facet_id": 69140,
            "occurrence": 16,
            "value": "Förster, Ernst (1800-1885)"
        },
        {
            "facet_id": 28454,
            "occurrence": 15,
            "value": "Brandis, Christian August (1790-1867)"
        },
        {
            "facet_id": 13,
            "occurrence": 14,
            "value": "Deutsche Forschungsgemeinschaft"
        },
        {
            "facet_id": 243446,
            "occurrence": 14,
            "value": "Hippel, Theodor Gottlieb von (1775-1843)"
        },
        {
            "facet_id": 149973,
            "occurrence": 13,
            "value": "Erman, Adolf (1806-1877)"
        },
        {
            "facet_id": 78460,
            "occurrence": 12,
            "value": "Kleist, Heinrich von (1777-1811)"
        },
        {
            "facet_id": 13224,
            "occurrence": 11,
            "value": "Preußische Akademie der Wissenschaften (Berlin)"
        },
        {
            "facet_id": 103477,
            "occurrence": 11,
            "value": "Wette, Wilhelm Martin Leberecht de (1780-1849)"
        },
        {
            "facet_id": 101934,
            "occurrence": 9,
            "value": "Niebuhr, Barthold Georg (1776-1831)"
        },
        {
            "facet_id": 127870,
            "occurrence": 9,
            "value": "Hosemann, Theodor (1807-1875)"
        },
        {
            "facet_id": 17685,
            "occurrence": 8,
            "value": "Crelle, August L. (1780-1855)"
        },
        {
            "facet_id": 38959,
            "occurrence": 8,
            "value": "Lachmann, Karl (1793-1851)"
        },
        {
            "facet_id": 95590,
            "occurrence": 8,
            "value": "Gurlt, Ernst Friedrich (1794-1882)"
        },
        {
            "facet_id": 1266,
            "occurrence": 7,
            "value": "Staatsbibliothek zu Berlin - Preußischer Kulturbesitz, Germany"
        },
        {
            "facet_id": 5398,
            "occurrence": 6,
            "value": "Burmeister, Hermann (1807-1892)"
        },
        {
            "facet_id": 24164,
            "occurrence": 6,
            "value": "Humboldt, Wilhelm von (1767-1835)"
        },
        {
            "facet_id": 24607,
            "occurrence": 6,
            "value": "Gruppe, Otto Friedrich (1804-1876)"
        },
        {
            "facet_id": 30736,
            "occurrence": 6,
            "value": "Varnhagen von Ense, Karl August (1785-1858)"
        },
        {
            "facet_id": 71148,
            "occurrence": 6,
            "value": "Albrecht <Friedland, Herzog> (1583-1634)"
        },
        {
            "facet_id": 115444,
            "occurrence": 6,
            "value": "Förster, Friedrich Christoph (1791-1868)"
        },
        {
            "facet_id": 20007,
            "occurrence": 5,
            "value": "Dindorf, Ludwig August (1805-1871)"
        },
        {
            "facet_id": 47723,
            "occurrence": 5,
            "value": "Walther, Philipp Franz von (1782-1849)"
        },
        {
            "facet_id": 59129,
            "occurrence": 5,
            "value": "Meineke, August (1790-1870)"
        },
        {
            "facet_id": 92665,
            "occurrence": 5,
            "value": "Remak, Robert"
        },
        {
            "facet_id": 110769,
            "occurrence": 5,
            "value": "Bülow, Eduard von (1803-1853)"
        },
        {
            "facet_id": 449110,
            "occurrence": 5,
            "value": "Eschscholtz, Johann Friedrich von (1793-1831)"
        },
        {
            "facet_id": 884,
            "occurrence": 4,
            "value": "Luther, Martin (1483-1546)"
        },
        {
            "facet_id": 9525,
            "occurrence": 4,
            "value": "Pertz, Georg Heinrich (1795-1876)"
        },
        {
            "facet_id": 12020,
            "occurrence": 4,
            "value": "Schröder, Friedrich Ludwig (1744-1816)"
        },
        {
            "facet_id": 16629,
            "occurrence": 4,
            "value": "Otto, Christian (1763-1828)"
        },
        {
            "facet_id": 33776,
            "occurrence": 4,
            "value": "Cervantes Saavedra, Miguel de (1547-1616)"
        },
        {
            "facet_id": 58922,
            "occurrence": 4,
            "value": "Gerhard, Eduard (1795-1867)"
        },
        {
            "facet_id": 87840,
            "occurrence": 4,
            "value": "Dove, Heinrich Wilhelm (1803-1879)"
        },
        {
            "facet_id": 130319,
            "occurrence": 4,
            "value": "Nesselmann, Ferdinand (1811-1881)"
        },
        {
            "facet_id": 203977,
            "occurrence": 4,
            "value": "Schrader, Eberhard"
        },
        {
            "facet_id": 205229,
            "occurrence": 4,
            "value": "Seidemann, Johann Karl (1807-1879)"
        },
        {
            "facet_id": 266405,
            "occurrence": 4,
            "value": "Rosenthal, C. A."
        },
        {
            "facet_id": 558449,
            "occurrence": 4,
            "value": "Scheibert, Carl Gottfried"
        },
        {
            "facet_id": 563120,
            "occurrence": 4,
            "value": "Grassmann, F. H."
        },
        {
            "facet_id": 569031,
            "occurrence": 4,
            "value": "Goetz, Jacob"
        },
        {
            "facet_id": 719,
            "occurrence": 3,
            "value": "Ovidius Naso, Publius (ca. 43 v. Chr.-ca. 18)"
        },
        {
            "facet_id": 10315,
            "occurrence": 3,
            "value": "Xenophon (v. 430-v. 355)"
        },
        {
            "facet_id": 13579,
            "occurrence": 3,
            "value": "Schlegel, Friedrich von (1772-1829)"
        },
        {
            "facet_id": 16456,
            "occurrence": 3,
            "value": "Livius, Titus (v59-17)"
        },
        {
            "facet_id": 27381,
            "occurrence": 3,
            "value": "Isler, Meyer (1807-1888)"
        },
        {
            "facet_id": 32279,
            "occurrence": 3,
            "value": "Erman, Adolf"
        },
        {
            "facet_id": 57480,
            "occurrence": 3,
            "value": "Feister"
        },
        {
            "facet_id": 62602,
            "occurrence": 3,
            "value": "Novalis (1772-1801)"
        },
        {
            "facet_id": 66823,
            "occurrence": 3,
            "value": "Eytelwein, Johann Albert (1764-1848)"
        },
        {
            "facet_id": 69518,
            "occurrence": 3,
            "value": "Merkel, Rudolph (1811-1885)"
        },
        {
            "facet_id": 74240,
            "occurrence": 3,
            "value": "Humboldt, Alexander von (1769-1859)"
        },
        {
            "facet_id": 78141,
            "occurrence": 3,
            "value": "Eschwege, Wilhelm Ludwig von (1777-1855)"
        },
        {
            "facet_id": 87874,
            "occurrence": 3,
            "value": "Lenz, Jakob Michael Reinhold (1751-1792)"
        },
        {
            "facet_id": 105189,
            "occurrence": 3,
            "value": "Ellendorf, Johann Otto (1806-1843)"
        },
        {
            "facet_id": 105216,
            "occurrence": 3,
            "value": "Heffter, August Wilhelm (1796-1880)"
        },
        {
            "facet_id": 124952,
            "occurrence": 3,
            "value": "Gaius (ca. gest. nach 178)"
        },
        {
            "facet_id": 127364,
            "occurrence": 3,
            "value": "Gesellschaft für Geburtshülfe (Berlin)"
        },
        {
            "facet_id": 169619,
            "occurrence": 3,
            "value": "Tigerström, Friedrich Wilhelm von (1803-1868)"
        },
        {
            "facet_id": 191148,
            "occurrence": 3,
            "value": "Crelle, August L."
        },
        {
            "facet_id": 212385,
            "occurrence": 3,
            "value": "Zimmermann, Carl (1813-1861)"
        },
        {
            "facet_id": 293800,
            "occurrence": 3,
            "value": "Jäsche, Gottlob Benjamin (1762-1842)"
        },
        {
            "facet_id": 314803,
            "occurrence": 3,
            "value": "Villaume, A."
        },
        {
            "facet_id": 330799,
            "occurrence": 3,
            "value": "Crelle, August Leopold"
        },
        {
            "facet_id": 355913,
            "occurrence": 3,
            "value": "Raschig, Franz Eduard (1802-1866)"
        },
        {
            "facet_id": 500338,
            "occurrence": 3,
            "value": "Usteri, Johann Martin (1763-1827)"
        },
        {
            "facet_id": 502105,
            "occurrence": 3,
            "value": "Dove, Heinrich Wilhelm"
        },
        {
            "facet_id": 517655,
            "occurrence": 3,
            "value": "Lützow, Carl von (1832-1897)"
        },
        {
            "facet_id": 537373,
            "occurrence": 3,
            "value": "Hess, David (1770-1843)"
        },
        {
            "facet_id": 1264,
            "occurrence": 2,
            "value": "Hogguér, Daniel"
        },
        {
            "facet_id": 3293,
            "occurrence": 2,
            "value": "Müller, Wilhelm"
        },
        {
            "facet_id": 3503,
            "occurrence": 2,
            "value": "Sugenheim, Samuel (1811-1877)"
        },
        {
            "facet_id": 3582,
            "occurrence": 2,
            "value": "Leupoldt, Johann Michael (1794-1874)"
        },
        {
            "facet_id": 5327,
            "occurrence": 2,
            "value": "Brandis, Joachim Dietrich (1762-1846)"
        },
        {
            "facet_id": 16040,
            "occurrence": 2,
            "value": "Paracelsus (1493-1541)"
        },
        {
            "facet_id": 18594,
            "occurrence": 2,
            "value": "Diodorus <Siculus> (ca. 60 v. Chr.-ca. 30 v. Chr.)"
        },
        {
            "facet_id": 20744,
            "occurrence": 2,
            "value": "Walther <von der Vogelweide> (1170-1230)"
        },
        {
            "facet_id": 32458,
            "occurrence": 2,
            "value": "Berghaus, Heinrich Karl Wilhelm (1797-1884)"
        },
        {
            "facet_id": 32536,
            "occurrence": 2,
            "value": "Pausanias <Periegeta> (ca. 2. Jh.)"
        },
        {
            "facet_id": 47940,
            "occurrence": 2,
            "value": "Roon, Albrecht Theodor Emil von (1803-1879)"
        },
        {
            "facet_id": 51081,
            "occurrence": 2,
            "value": "Schultz-Schultzenstein, Karl Heinrich (1798-1871)"
        },
        {
            "facet_id": 51167,
            "occurrence": 2,
            "value": "Hamann, Johann Georg (1730-1788)"
        },
        {
            "facet_id": 65019,
            "occurrence": 2,
            "value": "Aegidi, Ludwig Karl (1825-1901)"
        },
        {
            "facet_id": 71145,
            "occurrence": 2,
            "value": "Berends, Karl August Wilhelm (1759-1826)"
        },
        {
            "facet_id": 101028,
            "occurrence": 2,
            "value": "Schumann, Adolf (um 1847)"
        },
        {
            "facet_id": 104081,
            "occurrence": 2,
            "value": "Rademacher, Johann Gottfried (1772-1850)"
        },
        {
            "facet_id": 112467,
            "occurrence": 2,
            "value": "Du Bois- Reymond, Emil Heinrich (1818-1896)"
        }
    ]
}